moonshine_lite/__init__.py
moonshine_lite/cli.py
moonshine_lite/moonshine.py
moonshine_lite/data/__init__.py
moonshine_lite/data/tokenizer.json
moonshine_lite-0.0.3.dist-info/LICENSE
moonshine_lite-0.0.3.dist-info/METADATA
moonshine_lite-0.0.3.dist-info/WHEEL
moonshine_lite-0.0.3.dist-info/entry_points.txt
moonshine_lite-0.0.3.dist-info/top_level.txt
moonshine_lite-0.0.3.dist-info/RECORD
