Metadata-Version: 2.1
Name: moonshine-lite
Version: 0.0.3
Summary: Lite wrapper for the useful-moonshine speech to text models
Author-email: Yaser Martinez Palenzuela <yaser.martinez@gmail.com>
Project-URL: Homepage, https://elyase.github.io/moonshine-lite/
Project-URL: Repository, https://github.com/elyase/moonshine-lite
Project-URL: Documentation, https://elyase.github.io/moonshine-lite/
Keywords: python
Classifier: Intended Audience :: Developers
Classifier: Programming Language :: Python
Classifier: Programming Language :: Python :: 3
Classifier: Programming Language :: Python :: 3.9
Classifier: Programming Language :: Python :: 3.10
Classifier: Programming Language :: Python :: 3.11
Classifier: Programming Language :: Python :: 3.12
Classifier: Programming Language :: Python :: 3.13
Classifier: Topic :: Software Development :: Libraries :: Python Modules
Requires-Python: <4.0,>=3.9
License-File: LICENSE
Requires-Dist: huggingface-hub >=0.26.2
Requires-Dist: onnxruntime >=1.20.0
Requires-Dist: pynput >=1.7.7
Requires-Dist: silero-vad >=5.1.2
Requires-Dist: sounddevice >=0.5.1
Requires-Dist: tokenizers >=0.20.3
